framework/__init__.py
framework/runner.py
framework/utils.py
framework/validators.py
framework/scraper_spec_templates/config.yaml
framework/scraper_spec_templates/commands/baseline.md
framework/scraper_spec_templates/commands/discover.md
framework/scraper_spec_templates/commands/init.md
framework/scraper_spec_templates/commands/pull.md
framework/scraper_spec_templates/commands/push.md
framework/scraper_spec_templates/commands/release.md
framework/scraper_spec_templates/commands/test.md
framework/scraper_spec_templates/memory/constitution.md
framework/scraper_spec_templates/templates/baseline-template.json
framework/scraper_spec_templates/templates/debug-log-template.json
framework/scraper_spec_templates/templates/debug-report-template.md
framework/scraper_spec_templates/templates/diff-template.json
framework/scraper_spec_templates/templates/log-template.json
framework/scraper_spec_templates/templates/plan-template.md
framework/scraper_spec_templates/templates/selectors-template.yaml
scraper_spec-0.1.0.dist-info/licenses/LICENSE
scraper_spec-0.1.0.dist-info/METADATA
scraper_spec-0.1.0.dist-info/WHEEL
scraper_spec-0.1.0.dist-info/entry_points.txt
scraper_spec-0.1.0.dist-info/top_level.txt
scraper_spec-0.1.0.dist-info/RECORD
