Metadata-Version: 2.4
Name: scraper-spec
Version: 0.1.0
Summary: Site-agnostic specification framework for scraping automation engineers
Author-email: Scraper Spec Maintainers <maintainers@example.com>
License: MIT
Project-URL: Homepage, https://github.com/rainbowgore/scraping-spec-kit
Project-URL: Repository, https://github.com/rainbowgore/scraping-spec-kit
Project-URL: Documentation, https://github.com/rainbowgore/scraping-spec-kit/blob/main/README.md
Project-URL: Issues, https://github.com/rainbowgore/scraping-spec-kit/issues
Keywords: scraping,automation,testing,framework,specification,governance
Classifier: Development Status :: 3 - Alpha
Classifier: Intended Audience :: Developers
Classifier: Topic :: Software Development :: Testing
Classifier: Topic :: Internet :: WWW/HTTP
Classifier: License :: OSI Approved :: MIT License
Classifier: Programming Language :: Python :: 3
Classifier: Programming Language :: Python :: 3.8
Classifier: Programming Language :: Python :: 3.9
Classifier: Programming Language :: Python :: 3.10
Classifier: Programming Language :: Python :: 3.11
Classifier: Programming Language :: Python :: 3.12
Requires-Python: >=3.8
License-File: LICENSE
Requires-Dist: jsonschema>=4.0.0
Requires-Dist: PyYAML>=6.0
Dynamic: license-file
